VideoInfo/Mp4Url.py
VideoInfo/VideoBase.py
VideoInfo/__init__.py
VideoInfo/parse.py
VideoInfo-1.0.dist-info/LICENSE
VideoInfo-1.0.dist-info/METADATA
VideoInfo-1.0.dist-info/WHEEL
VideoInfo-1.0.dist-info/top_level.txt
VideoInfo-1.0.dist-info/RECORD
