Metadata-Version: 2.1
Name: VideoInfo
Version: 1.0
Summary: parse online video file metadata
Home-page: https://www.github.com/kentxxq/VideoInfo
Author: kentxxq
Author-email: admin@kentxxq.com
License: UNKNOWN
Platform: UNKNOWN
Classifier: Programming Language :: Python :: 3.7
Classifier: License :: OSI Approved :: MIT License
Classifier: Operating System :: OS Independent
Requires-Python: >=3.7
Requires-Dist: construct (==2.8.8)
Requires-Dist: requests (==2.22.0)
